README.rst
setup.py
compose_addons/__init__.py
compose_addons/config_utils.py
compose_addons/includes.py
compose_addons/merge.py
compose_addons/namespace.py
compose_addons.egg-info/PKG-INFO
compose_addons.egg-info/SOURCES.txt
compose_addons.egg-info/dependency_links.txt
compose_addons.egg-info/entry_points.txt
compose_addons.egg-info/requires.txt
compose_addons.egg-info/top_level.txt