Metadata-Version: 1.1
Name: compose-addons
Version: 0.2.1
Summary: Tools to supplement
Home-page: http://github.com/dnephin/compose-addons
Author: Daniel Nephin
Author-email: dnephin@gmail.com
License: Apache License 2.0
Platform: UNKNOWN
Classifier: Programming Language :: Python
Classifier: Operating System :: OS Independent
Classifier: License :: OSI Approved :: Apache Software License
Classifier: Intended Audience :: Developers
Provides: compose_addons
